Metadata-Version: 1.0
Name: trackely-client
Version: 1.0.0rc10
Summary: Client for trackely service
Home-page: https://github.com/gamikun/trackely-client-python
Author: Gamaliel Espinoza
Author-email: gamaliel.espinoza@gmail.com
License: UNKNOWN
Keywords: trackely
Platform: UNKNOWN
